{
  "id": 3,
  "title": "spark-oktawave cluster overview",
  "description": "Based on https://grafana.com/dashboards/24",
  "tags": [
    "collectd",
    "spark"
  ],
  "style": "dark",
  "timezone": "browser",
  "editable": true,
  "sharedCrosshair": true,
  "hideControls": false,
  "time": {
    "from": "now-5m",
    "to": "now"
  },
  "timepicker": {
    "now": true,
    "refresh_intervals": [
      "5s",
      "10s",
      "30s",
      "1m",
      "5m",
      "15m",
      "30m",
      "1h",
      "2h",
      "1d"
    ],
    "time_options": [
      "5m",
      "15m",
      "1h",
      "6h",
      "12h",
      "24h",
      "2d",
      "7d",
      "30d"
    ]
  },
  "templating": {
    "list": [
      {
        "allValue": null,
        "current": {
          "selected": true,
          "text": "spark0",
          "value": "spark0"
        },
        "datasource": "graphite",
        "hide": 0,
        "includeAll": false,
        "label": null,
        "multi": false,
        "name": "cluster",
        "options": [
          {
            "selected": true,
            "text": "spark0",
            "value": "spark0"
          }
        ],
        "query": "spark_oktawave.*",
        "refresh": 0,
        "regex": "",
        "sort": 0,
        "tagValuesQuery": null,
        "tagsQuery": null,
        "type": "query"
      },
      {
        "allFormat": "glob",
        "allValue": null,
        "current": {
          "text": "All",
          "value": "$__all"
        },
        "datasource": "graphite",
        "hide": 0,
        "includeAll": true,
        "label": null,
        "multi": false,
        "multiFormat": "glob",
        "name": "server",
        "options": [],
        "query": "spark_oktawave.$cluster.*",
        "refresh": 1,
        "refresh_on_load": false,
        "regex": "",
        "sort": 0,
        "tagValuesQuery": null,
        "tagsQuery": null,
        "type": "query"
      }
    ]
  },
  "annotations": {
    "list": []
  },
  "refresh": "10s",
  "schemaVersion": 13,
  "version": 7,
  "links": [],
  "gnetId": 24,
  "rows": [
    {
      "title": "New row",
      "panels": [
        {
          "aliasColors": {
            "1.steal": "#E24D42",
            "steal": "#E24D42"
          },
          "bars": false,
          "datasource": "graphite",
          "editable": true,
          "error": false,
          "fill": 2,
          "grid": {},
          "id": 15,
          "legend": {
            "alignAsTable": true,
            "avg": true,
            "current": false,
            "hideZero": false,
            "max": false,
            "min": false,
            "rightSide": true,
            "show": false,
            "total": false,
            "values": true
          },
          "lines": true,
          "linewidth": 2,
          "links": [],
          "nullPointMode": "connected",
          "percentage": false,
          "pointradius": 5,
          "points": false,
          "renderer": "flot",
          "seriesOverrides": [],
          "span": 6,
          "stack": true,
          "steppedLine": false,
          "targets": [
            {
              "refId": "A",
              "target": "aliasByNode(spark_oktawave.$cluster.$server.aggregation.cpu-average.cpu.{system,wait,user}, 6)",
              "textEditor": true
            }
          ],
          "thresholds": [],
          "timeFrom": null,
          "timeShift": null,
          "title": "CPU Average",
          "tooltip": {
            "msResolution": false,
            "shared": true,
            "sort": 0,
            "value_type": "individual"
          },
          "type": "graph",
          "xaxis": {
            "mode": "time",
            "name": null,
            "show": true,
            "values": []
          },
          "yaxes": [
            {
              "format": "percent",
              "logBase": 1,
              "max": null,
              "min": 0,
              "show": true
            },
            {
              "format": "short",
              "logBase": 1,
              "max": null,
              "min": null,
              "show": true
            }
          ]
        },
        {
          "aliasColors": {},
          "bars": false,
          "datasource": "graphite",
          "editable": true,
          "error": false,
          "fill": 1,
          "grid": {},
          "id": 10,
          "legend": {
            "alignAsTable": true,
            "avg": true,
            "current": false,
            "max": false,
            "min": false,
            "rightSide": true,
            "show": true,
            "total": false,
            "values": true
          },
          "lines": true,
          "linewidth": 2,
          "links": [],
          "nullPointMode": "connected",
          "percentage": false,
          "pointradius": 5,
          "points": false,
          "renderer": "flot",
          "seriesOverrides": [],
          "span": 6,
          "stack": true,
          "steppedLine": false,
          "targets": [
            {
              "refId": "A",
              "target": "aliasByNode(spark_oktawave.$cluster.$server.memory.memory.{cached,free,buffered}, 5)",
              "textEditor": true
            }
          ],
          "thresholds": [],
          "timeFrom": null,
          "timeShift": null,
          "title": "Memory Available",
          "tooltip": {
            "msResolution": true,
            "shared": true,
            "sort": 0,
            "value_type": "individual"
          },
          "type": "graph",
          "xaxis": {
            "mode": "time",
            "name": null,
            "show": true,
            "values": []
          },
          "yaxes": [
            {
              "format": "bits",
              "logBase": 1,
              "max": null,
              "min": 0,
              "show": true
            },
            {
              "format": "short",
              "logBase": 1,
              "max": null,
              "min": null,
              "show": true
            }
          ]
        }
      ],
      "showTitle": false,
      "titleSize": "h6",
      "height": "250px",
      "repeat": null,
      "repeatRowId": null,
      "repeatIteration": null,
      "collapse": false
    },
    {
      "title": "New row",
      "panels": [
        {
          "aliasColors": {},
          "bars": false,
          "datasource": "graphite",
          "editable": true,
          "error": false,
          "fill": 1,
          "grid": {},
          "id": 3,
          "legend": {
            "alignAsTable": true,
            "avg": true,
            "current": false,
            "max": false,
            "min": false,
            "rightSide": true,
            "show": false,
            "total": false,
            "values": true
          },
          "lines": true,
          "linewidth": 2,
          "links": [],
          "nullPointMode": "connected",
          "percentage": false,
          "pointradius": 5,
          "points": false,
          "renderer": "flot",
          "seriesOverrides": [],
          "span": 4,
          "stack": false,
          "steppedLine": false,
          "targets": [
            {
              "refId": "A",
              "target": "aliasByNode(spark_oktawave.$cluster.$server.load.load.shortterm, 2)",
              "textEditor": true
            }
          ],
          "thresholds": [],
          "timeFrom": null,
          "timeShift": null,
          "title": "Load",
          "tooltip": {
            "msResolution": false,
            "shared": true,
            "sort": 0,
            "value_type": "individual"
          },
          "type": "graph",
          "xaxis": {
            "mode": "time",
            "name": null,
            "show": true,
            "values": []
          },
          "yaxes": [
            {
              "format": "short",
              "logBase": 1,
              "max": null,
              "min": null,
              "show": true
            },
            {
              "format": "short",
              "logBase": 1,
              "max": null,
              "min": null,
              "show": true
            }
          ]
        },
        {
          "aliasColors": {},
          "bars": false,
          "datasource": "graphite",
          "editable": true,
          "error": false,
          "fill": 1,
          "grid": {},
          "id": 5,
          "legend": {
            "avg": false,
            "current": false,
            "max": false,
            "min": false,
            "show": false,
            "total": false,
            "values": false
          },
          "lines": true,
          "linewidth": 2,
          "links": [],
          "nullPointMode": "connected",
          "percentage": false,
          "pointradius": 5,
          "points": false,
          "renderer": "flot",
          "seriesOverrides": [],
          "span": 2,
          "stack": false,
          "steppedLine": false,
          "targets": [
            {
              "refId": "A",
              "target": "alias(perSecond(spark_oktawave.$cluster.$server.processes.fork_rate), 'new processes')",
              "textEditor": true
            }
          ],
          "thresholds": [],
          "timeFrom": null,
          "timeShift": null,
          "title": "Process Fork/sec",
          "tooltip": {
            "msResolution": false,
            "shared": true,
            "sort": 0,
            "value_type": "cumulative"
          },
          "type": "graph",
          "xaxis": {
            "mode": "time",
            "name": null,
            "show": true,
            "values": []
          },
          "yaxes": [
            {
              "format": "short",
              "logBase": 1,
              "max": null,
              "min": null,
              "show": true
            },
            {
              "format": "short",
              "logBase": 1,
              "max": null,
              "min": null,
              "show": true
            }
          ]
        },
        {
          "aliasColors": {},
          "bars": false,
          "datasource": "graphite",
          "editable": true,
          "error": false,
          "fill": 1,
          "grid": {},
          "id": 4,
          "legend": {
            "avg": false,
            "current": false,
            "max": false,
            "min": false,
            "show": true,
            "total": false,
            "values": false
          },
          "lines": true,
          "linewidth": 2,
          "links": [],
          "nullPointMode": "connected",
          "percentage": false,
          "pointradius": 5,
          "points": false,
          "renderer": "flot",
          "seriesOverrides": [],
          "span": 6,
          "stack": false,
          "steppedLine": false,
          "targets": [
            {
              "refId": "A",
              "target": "aliasByNode(spark_oktawave.$cluster.$server.processes.ps_state.*, 5)",
              "textEditor": true
            }
          ],
          "thresholds": [],
          "timeFrom": null,
          "timeShift": null,
          "title": "Processes",
          "tooltip": {
            "msResolution": false,
            "shared": true,
            "sort": 0,
            "value_type": "cumulative"
          },
          "type": "graph",
          "xaxis": {
            "mode": "time",
            "name": null,
            "show": true,
            "values": []
          },
          "yaxes": [
            {
              "format": "short",
              "logBase": 1,
              "max": null,
              "min": null,
              "show": true
            },
            {
              "format": "short",
              "logBase": 1,
              "max": null,
              "min": null,
              "show": true
            }
          ]
        }
      ],
      "showTitle": false,
      "titleSize": "h6",
      "height": "250px",
      "repeat": null,
      "repeatRowId": null,
      "repeatIteration": null,
      "collapse": false
    },
    {
      "title": "New row",
      "panels": [
        {
          "aliasColors": {},
          "bars": false,
          "datasource": "graphite",
          "editable": true,
          "error": false,
          "fill": 1,
          "grid": {},
          "id": 7,
          "legend": {
            "avg": false,
            "current": false,
            "max": false,
            "min": false,
            "show": true,
            "total": false,
            "values": false
          },
          "lines": false,
          "linewidth": 2,
          "links": [],
          "nullPointMode": "connected",
          "percentage": false,
          "pointradius": 1,
          "points": true,
          "renderer": "flot",
          "seriesOverrides": [],
          "span": 4,
          "stack": false,
          "steppedLine": false,
          "targets": [
            {
              "refId": "A",
              "target": "aliasByNode(perSecond(spark_oktawave.$cluster.$server.disk.dm-0.disk_ops.read), 2)",
              "textEditor": true
            }
          ],
          "thresholds": [],
          "timeFrom": null,
          "timeShift": null,
          "title": "Read IOPS",
          "tooltip": {
            "msResolution": false,
            "shared": true,
            "sort": 0,
            "value_type": "cumulative"
          },
          "type": "graph",
          "xaxis": {
            "mode": "time",
            "name": null,
            "show": true,
            "values": []
          },
          "yaxes": [
            {
              "format": "short",
              "logBase": 1,
              "max": null,
              "min": null,
              "show": true
            },
            {
              "format": "short",
              "logBase": 1,
              "max": null,
              "min": null,
              "show": true
            }
          ]
        },
        {
          "aliasColors": {},
          "bars": false,
          "datasource": "graphite",
          "editable": true,
          "error": false,
          "fill": 1,
          "grid": {},
          "id": 8,
          "legend": {
            "avg": false,
            "current": false,
            "max": false,
            "min": false,
            "show": true,
            "total": false,
            "values": false
          },
          "lines": false,
          "linewidth": 2,
          "links": [],
          "nullPointMode": "connected",
          "percentage": false,
          "pointradius": 1,
          "points": true,
          "renderer": "flot",
          "seriesOverrides": [],
          "span": 4,
          "stack": false,
          "steppedLine": false,
          "targets": [
            {
              "refId": "A",
              "target": "aliasByNode(perSecond(spark_oktawave.$cluster.$server.disk.dm-0.disk_ops.write), 2)",
              "textEditor": true
            }
          ],
          "thresholds": [],
          "timeFrom": null,
          "timeShift": null,
          "title": "Write IOPS",
          "tooltip": {
            "msResolution": false,
            "shared": true,
            "sort": 0,
            "value_type": "cumulative"
          },
          "type": "graph",
          "xaxis": {
            "mode": "time",
            "name": null,
            "show": true,
            "values": []
          },
          "yaxes": [
            {
              "format": "short",
              "logBase": 1,
              "max": null,
              "min": null,
              "show": true
            },
            {
              "format": "short",
              "logBase": 1,
              "max": null,
              "min": null,
              "show": true
            }
          ]
        },
        {
          "aliasColors": {},
          "bars": false,
          "datasource": "graphite",
          "editable": true,
          "error": false,
          "fill": 1,
          "grid": {},
          "id": 2,
          "legend": {
            "alignAsTable": true,
            "avg": true,
            "current": false,
            "max": false,
            "min": false,
            "rightSide": true,
            "show": false,
            "total": false,
            "values": true
          },
          "lines": true,
          "linewidth": 2,
          "links": [],
          "nullPointMode": "connected",
          "percentage": false,
          "pointradius": 5,
          "points": false,
          "renderer": "flot",
          "seriesOverrides": [],
          "span": 4,
          "stack": false,
          "steppedLine": false,
          "targets": [
            {
              "refId": "A",
              "target": "aliasByNode(spark_oktawave.$cluster.$server.df.root.percent_bytes.used, 2)",
              "textEditor": false
            }
          ],
          "thresholds": [],
          "timeFrom": null,
          "timeShift": null,
          "title": "Disk Usage",
          "tooltip": {
            "msResolution": true,
            "shared": true,
            "sort": 0,
            "value_type": "individual"
          },
          "type": "graph",
          "xaxis": {
            "mode": "time",
            "name": null,
            "show": true,
            "values": []
          },
          "yaxes": [
            {
              "format": "percent",
              "logBase": 1,
              "max": 100,
              "min": 0,
              "show": true
            },
            {
              "format": "short",
              "logBase": 1,
              "max": null,
              "min": null,
              "show": true
            }
          ]
        }
      ],
      "showTitle": false,
      "titleSize": "h6",
      "height": "250px",
      "repeat": null,
      "repeatRowId": null,
      "repeatIteration": null,
      "collapse": false
    },
    {
      "title": "New row",
      "panels": [
        {
          "aliasColors": {},
          "bars": false,
          "datasource": "graphite",
          "editable": true,
          "error": false,
          "fill": 1,
          "grid": {},
          "id": 9,
          "legend": {
            "avg": false,
            "current": false,
            "max": false,
            "min": false,
            "show": true,
            "total": false,
            "values": false
          },
          "lines": true,
          "linewidth": 2,
          "links": [],
          "nullPointMode": "connected",
          "percentage": false,
          "pointradius": 5,
          "points": false,
          "renderer": "flot",
          "seriesOverrides": [
            {
              "alias": "/.*-out/",
              "transform": "negative-Y"
            }
          ],
          "span": 4,
          "stack": false,
          "steppedLine": false,
          "targets": [
            {
              "refId": "A",
              "target": "aliasSub(aliasByNode(scale(perSecond(spark_oktawave.$cluster.$server.interface.eth0.if_octets.rx), 8), 2), '(.*)', '\\1-in'))",
              "textEditor": true
            },
            {
              "refId": "B",
              "target": "aliasSub(aliasByNode(scale(perSecond(spark_oktawave.$cluster.$server.interface.eth0.if_octets.tx), 8), 2), '(.*)', '\\1-out'))",
              "textEditor": true
            }
          ],
          "thresholds": [],
          "timeFrom": null,
          "timeShift": null,
          "title": "Network Traffic/sec",
          "tooltip": {
            "msResolution": true,
            "shared": true,
            "sort": 0,
            "value_type": "cumulative"
          },
          "type": "graph",
          "xaxis": {
            "mode": "time",
            "name": null,
            "show": true,
            "values": []
          },
          "yaxes": [
            {
              "format": "bps",
              "logBase": 1,
              "max": null,
              "min": null,
              "show": true
            },
            {
              "format": "short",
              "logBase": 1,
              "max": null,
              "min": null,
              "show": true
            }
          ]
        },
        {
          "aliasColors": {},
          "bars": false,
          "datasource": "graphite",
          "editable": true,
          "error": false,
          "fill": 1,
          "grid": {},
          "id": 11,
          "legend": {
            "avg": false,
            "current": false,
            "max": false,
            "min": false,
            "show": true,
            "total": false,
            "values": false
          },
          "lines": true,
          "linewidth": 2,
          "links": [],
          "nullPointMode": "connected",
          "percentage": false,
          "pointradius": 5,
          "points": false,
          "renderer": "flot",
          "seriesOverrides": [
            {
              "alias": "/.*-out/",
              "transform": "negative-Y"
            }
          ],
          "span": 4,
          "stack": false,
          "steppedLine": false,
          "targets": [
            {
              "refId": "A",
              "target": "aliasSub(aliasByNode(removeBelowValue(perSecond(spark_oktawave.$cluster.$server.interface.eth0.if_errors.rx), 1), 2), '(.*)', '\\1-in')",
              "textEditor": true
            },
            {
              "refId": "B",
              "target": "aliasSub(aliasByNode(removeBelowValue(perSecond(spark_oktawave.$cluster.$server.interface.eth0.if_errors.tx), 1), 2), '(.*)', '\\1-out')",
              "textEditor": true
            }
          ],
          "thresholds": [],
          "timeFrom": null,
          "timeShift": null,
          "title": "Network Errors/sec",
          "tooltip": {
            "msResolution": false,
            "shared": true,
            "sort": 0,
            "value_type": "cumulative"
          },
          "type": "graph",
          "xaxis": {
            "mode": "time",
            "name": null,
            "show": true,
            "values": []
          },
          "yaxes": [
            {
              "format": "none",
              "logBase": 1,
              "max": null,
              "min": null,
              "show": true
            },
            {
              "format": "short",
              "logBase": 1,
              "max": null,
              "min": null,
              "show": true
            }
          ]
        },
        {
          "aliasColors": {},
          "bars": false,
          "datasource": "graphite",
          "editable": true,
          "error": false,
          "fill": 1,
          "grid": {},
          "id": 12,
          "legend": {
            "avg": false,
            "current": false,
            "max": false,
            "min": false,
            "show": true,
            "total": false,
            "values": false
          },
          "lines": true,
          "linewidth": 2,
          "links": [],
          "nullPointMode": "connected",
          "percentage": false,
          "pointradius": 5,
          "points": false,
          "renderer": "flot",
          "seriesOverrides": [
            {
              "alias": "/.*-out/",
              "transform": "negative-Y"
            }
          ],
          "span": 4,
          "stack": false,
          "steppedLine": false,
          "targets": [
            {
              "refId": "A",
              "target": "aliasSub(aliasByNode(perSecond(spark_oktawave.$cluster.$server.interface.eth0.if_packets.rx), 2), '(.*)', '\\1-in')",
              "textEditor": true
            },
            {
              "refId": "B",
              "target": "aliasSub(aliasByNode(perSecond(spark_oktawave.$cluster.$server.interface.eth0.if_packets.tx), 2), '(.*)', '\\1-out')",
              "textEditor": true
            }
          ],
          "thresholds": [],
          "timeFrom": null,
          "timeShift": null,
          "title": "Network Packets/sec",
          "tooltip": {
            "msResolution": false,
            "shared": true,
            "sort": 0,
            "value_type": "cumulative"
          },
          "type": "graph",
          "xaxis": {
            "mode": "time",
            "name": null,
            "show": true,
            "values": []
          },
          "yaxes": [
            {
              "format": "none",
              "logBase": 1,
              "max": null,
              "min": null,
              "show": true
            },
            {
              "format": "short",
              "logBase": 1,
              "max": null,
              "min": null,
              "show": true
            }
          ]
        }
      ],
      "showTitle": false,
      "titleSize": "h6",
      "height": "250px",
      "repeat": null,
      "repeatRowId": null,
      "repeatIteration": null,
      "collapse": false
    }
  ]
}